[
  {
    "metadata": [
      {
        "nimi": "Yleiset kielitutkinnot (YKI), keskitaso",
        "kuvaus": "",
        "lyhytNimi": "",
        "kieli": "FI"
      },
      {
        "nimi": "Allmänna språkexamina (YKI), mellannivå",
        "kuvaus": null,
        "kieli": "SV"
      },
      {
        "nimi": "National Certificates of Language Proficiency (YKI), intermediate level",
        "kuvaus": null,
        "kieli": "EN"
      }
    ],
    "withinCodeElements": [],
    "includesCodeElements": [],
    "levelsWithCodeElements": [],
    "koodiUri": "ykitutkintotaso_kt",
    "versio": 1,
    "koodiArvo": "kt"
  },
  {
    "metadata": [
      {
        "nimi": "Yleiset kielitutkinnot (YKI), perustaso",
        "kuvaus": "",
        "lyhytNimi": "",
        "kieli": "FI"
      },
      {
        "nimi": "Allmänna språkexamina (YKI), grundnivå",
        "kuvaus": null,
        "kieli": "SV"
      },
      {
        "nimi": "National Certificates of Language Proficiency (YKI), basic level",
        "kuvaus": null,
        "kieli": "EN"
      }
    ],
    "withinCodeElements": [],
    "includesCodeElements": [],
    "levelsWithCodeElements": [],
    "koodiUri": "ykitutkintotaso_pt",
    "versio": 1,
    "koodiArvo": "pt"
  },
  {
    "metadata": [
      {
        "nimi": "Yleiset kielitutkinnot (YKI), ylin taso",
        "kuvaus": "",
        "lyhytNimi": "",
        "kieli": "FI"
      },
      {
        "nimi": "Allmänna språkexamina (YKI), högsta nivå",
        "kuvaus": null,
        "kieli": "SV"
      },
      {
        "nimi": "National Certificates of Language Proficiency (YKI), advanced level",
        "kuvaus": null,
        "kieli": "EN"
      }
    ],
    "withinCodeElements": [],
    "includesCodeElements": [],
    "levelsWithCodeElements": [],
    "koodiUri": "ykitutkintotaso_yt",
    "versio": 1,
    "koodiArvo": "yt"
  }
]
