{
  "koodistoUri": "ytrtutkintokokonaisuudentila",
  "resourceUri": "https://virkailija.opintopolku.fi/koodisto-service/rest/codes/ytrtutkintokokonaisuudentila",
  "omistaja": null,
  "organisaatioOid": "1.2.246.562.10.00000000001",
  "lukittu": null,
  "withinCodes": [],
  "includesCodes": [],
  "levelsWithCodes": [],
  "codesGroupUri": "koski",
  "version": 0,
  "versio": 1,
  "paivitysPvm": "2023-03-01",
  "paivittajaOid": "1.2.246.562.24.98063222086",
  "voimassaAlkuPvm": "2016-09-09",
  "voimassaLoppuPvm": null,
  "tila": "LUONNOS",
  "metadata": [
    {
      "kieli": "SV",
      "nimi": "YTR tutkintokokonaisuuden tila",
      "kuvaus": null,
      "kayttoohje": null,
      "kasite": null,
      "kohdealue": null,
      "sitovuustaso": null,
      "kohdealueenOsaAlue": null,
      "toimintaymparisto": null,
      "tarkentaaKoodistoa": null,
      "huomioitavaKoodisto": null,
      "koodistonLahde": null
    },
    {
      "kieli": "FI",
      "nimi": "YTR tutkintokokonaisuuden tila",
      "kuvaus": "Tutkinnon tila",
      "kayttoohje": null,
      "kasite": null,
      "kohdealue": null,
      "sitovuustaso": null,
      "kohdealueenOsaAlue": null,
      "toimintaymparisto": null,
      "tarkentaaKoodistoa": null,
      "huomioitavaKoodisto": null,
      "koodistonLahde": null
    },
    {
      "kieli": "EN",
      "nimi": "YTR tutkintokokonaisuuden tila",
      "kuvaus": null,
      "kayttoohje": null,
      "kasite": null,
      "kohdealue": null,
      "sitovuustaso": null,
      "kohdealueenOsaAlue": null,
      "toimintaymparisto": null,
      "tarkentaaKoodistoa": null,
      "huomioitavaKoodisto": null,
      "koodistonLahde": null
    }
  ],
  "codesVersions": []
}
